{
"bseycrvgyn6sfrnoo7ivka6c":["justmorezowee","jzen"],
"ga32hvc335nz7lkvfhdyfeeg":["jzexyz","Jesus "],
"kp7dr5clafxjgm3gcrsij66a":["jzembik","Josh Zembik"],
"tcfdh5bgyom5qlqpmifpjcv5":"jzen",
"u7qi6hu7erfhixk3j7s66zrg":["jzellis","Joshua Ellis"],
"2magmesrtnpnauhr2yv2hjde":"jzee",
"cn6bgmddvgcyd7ya6yqai3u3":"jzero",
"xrftnravkobjigksmeyqyhnu":"jzebulonr",
"ryazlynottfqyz6fsmz55urm":["jzenith","Zenith"],
"lodgwdo6be2fasbafy5sqjd2":"jzems",
"kh46vwbrawuqtktzt4um6zzg":"jzer",
"7hehhg6irurmhxsskshtelj2":["jzero0","J zero "]
}
