{
"rckcp3dqp6qi5xvk3v62vhdq":["fiftyfour","JBC"],
"66mld4my5n72bw5m4nqr23zb":["jbcphotos","JBC"],
"ijmwtj6usfs32t3bmpx5ht5c":["jbc.is","Jut"],
"q4u5kyguvu6tf2ibs22egm2r":["jbcurio","Jamie Bradburn"],
"tm2pupdkpm3dmlne34omxgj5":["jbc3","Joe Calhoun"],
"fnrupszl75qecotzngbhkqhn":"jbcden",
"xbgtmhepedbejxxudl5ubnhb":"jbc",
"bz5fimjjiyltcpl5uuzbpehh":["jbcray","John B"],
"7d4w2pjybcjqjqql3aitze3h":["jbcarvalho","João Carvalho "],
"7s6mnotrmnt76gf4u52esrb5":"jbcastrocr",
"orsklgspi6is452lgquxp45z":"jbcarson",
"t2mx3lxlcafepyvoxgpw7h7r":["jbcurtin","Joseph Curtin ( jbcurtin )"],
"ytyywunfdofmv7xqqk6pn7eb":"jbcards170",
"72ton2qtbwjt6o3yng7lwfzu":["jbcogrom","JBCO"],
"aubx4lnc6ivrvo2t6pm2tmdv":["jbca","Jeremy"],
"hyfh6epspeqpbuopmd3iepzm":"jbchristman",
"rzgeybuqqb3cifwdxxnvtaqr":"jbclara",
"svf6wtfhyacxirg4qpxrjmim":"jbchsbeach",
"afghl65s7sbce6hn4uuftc3s":"jbclark",
"4oaukgqvhu6b7ro4flqflrrs":"jbcima",
"4acsg2fjg4xshce7sgh6zkhh":"jbcomposer",
"zgqnnnhp4z7lcyazqlg44xsw":["jbcouperin","Couperin"],
"pszkkhadwyl3vmigq2puvum7":["jbcamps","Jean-Baptiste Camps"],
"y5odmyx7tzdywwlhlfkkq5lc":["jbcblank","Artist_JBCBlank"],
"ut5mb3lphudsohpbsg2dqflu":["jbchabran","Jean-Baptiste Chabran"],
"rettvo5idoifohjnmn6aghho":["jbcrowe","J Crowe"],
"65ku4mcxx4z6fdolxaxbikj5":["jbcreations","JB Creations"],
"fl7z6crxyjkxsy2lrh34c2yw":"jbcyof",
"bq6mwmqe3hidua4q74ljfegd":"jbcasler",
"mouwslwbclh56bsjj4puwz4r":"jbcr",
"2fpi4f4vkrbn3mnt6uwlsvj7":["jibaycay","jbc 🍕🍍"],
"nd2xqpwrut2qsirw4dzru24r":["the999jbc","jbc to the 999th power"],
"m5ibwgg6ssmfxohpfrqn4p4g":["tochijbc","Tochi_jbc📊"]
}
