{
"yxgjq2xrj4olksaitliz6tuv":["cryptojesperk","Jesper - jtk.eth"],
"7x2nh2wxmgucwwf25yprshcm":["jtk1000","Jan Terje Kristiansen"],
"vsjs3knofrqwe6swl45syn4x":["jtk","JTK"],
"cxhb3gfoqgehkxyfobsszjeb":["jtk222","JTK222"],
"qbdygy4xjyhpmtnsg5j75yxo":"jtkehler",
"s4ifm2lhyc6g3ib7iaszfqzn":"jtk001",
"coxkxkvk3px7sevundobnot2":"jtknuds",
"7jyyz5mdptt6mqvwhxzbwi4j":["jtkelly","JT Kelly"],
"fjd7wz6rhk2jnr2uyrecf4sa":["jtkeller","JT Keller"],
"vx7hksgqjaiq6tb64bkyqpnm":"jtkrul",
"qsn6toys33ao3cigzzrqbabp":["jtkornel","Jan Tore Korneliussen"],
"ppeen55kk5c4zrxu4mka7k6h":"jtknopf",
"vmggque6sjf4tihsmudz4uxs":"jtk146",
"re4reablcx7eerwafdl3l3a4":"jtkoexnphs6zjb",
"vqakw2d7i4l23yqttvwvpvw2":["jtke","Janne Keskitalo"],
"uhemucwiica5wbbgnkv7utbs":["jtkiv","Thomas Kirkpatrick"],
"ivwmsadnnc5a3gsosu2mms3s":"jtkiaba",
"pjfx6d2ymtsu2butkbijauej":["jtkatie","Katie "],
"k4ll5rfxodubltmejxlvbaeu":["jtkirk","Kevin"],
"hjotmgpwholkpu3gsq3b7u63":"jtkearns",
"3zgxkwwaxxxhk6qnimwd4by4":["jtkirk0815","Stefan Hellendahl"],
"byf6klq7sne2shxjh5iszucs":["oldtank","JTK"]
}
