{
"zjncq6hdz74ktliaiiuzosaj":"jmymy",
"r7bybvtoxyrqxv7km2wfqkfs":["jmyales","Josephine Maria Yanasak-Leszczynski"],
"y6kfgniksqkh55oltyix4iob":"jmyers",
"evyy57rzncep4immka26yv5n":"jmyszka",
"sftbfkmibh3k2tgivorrr5di":["jmynyc","June Yearwood"],
"vazgk2i2wz72hnqui24tlelt":["jmyoda","Cheese Connoisseur "],
"jbvvwwt2zdqb4b73vt2nzrjv":"jmyjazz",
"injt5pd27hjhqs5dacdj4ftq":["jmyrechuck","J Myrechuck"],
"nvy3g442tl4zntrgm5iew5p3":["jmyearsley","James Yearsley"],
"z3u543y6i63pufuqm3nexo7m":"jmyerz1"
}
