{
"p4t537b4is547h773rueqqxi":["boyjix","boyJix"],
"a27soro2ggl2hklv7wyh2b3z":["jixxyjexxy","Jixxy the swamp hag"],
"hseyjviginfca4ktnl5luk35":["jixbyphillips","Jixby Phillips"],
"k3tclhdfh7dxnvau37r5asfj":["jixbee","Bee 🐝"],
"lx6qcagir6ujl2vpw4aqo6vv":["jix","z?"],
"e6fqdbyjeaxyapk4nkboymkh":["jixiepop","JixiePop🍭🏳️‍⚧️"],
"fjbbwyv7agxaenloajhbaew7":["jix.nitewoof.xyz","Jix Pneumothorax 🇨🇦"],
"2cvdb63fume3z625wa2gm6yu":"jixxr62",
"yocjv6u5bcsvht7o4qckr6mp":["jixstun","Jixstun"],
"nakekucrlkymycqbxqoifdzm":"jixy0",
"imzeqfn6qpbbgjiwp3wuzzux":["jixxy","Jixxy"],
"3netdlepuyissd2hh4gzxs4h":["nea-jix","Néa Jix"],
"hdbbnogaozotgtfhahzdibgr":["tecoandjix","TecoAndJix"]
}
